vnpy_insight/__init__.py
vnpy_insight/insight_datafeed.py
vnpy_insight/utils.py
vnpy_insight-0.1.1.dist-info/LICENSE
vnpy_insight-0.1.1.dist-info/METADATA
vnpy_insight-0.1.1.dist-info/WHEEL
vnpy_insight-0.1.1.dist-info/top_level.txt
vnpy_insight-0.1.1.dist-info/RECORD
