Metadata-Version: 2.1
Name: vnpy-insight
Version: 0.1.1
Summary: 用于vnpy获取历史数据的华泰insight接口
Author: kangyuqiang
Author-email: kangyuqiang123@gmail.com
License: UNKNOWN
Keywords: vnpy,insight,华泰,huatai
Platform: UNKNOWN
Classifier: Programming Language :: Python :: 3
Classifier: License :: OSI Approved :: Apache Software License
Classifier: Operating System :: OS Independent
License-File: LICENSE
Requires-Dist: insight-sdk (==4.0.7)
